{
  "ok": true,
  "dry_run": false,
  "no_persist": false,
  "rollback_smoke": false,
  "contract_status": "quoted",
  "owner_civilization_id": "00000000-0000-4000-8000-000000000001",
  "rental_contract_id": "51c1f7e5-b06c-450c-8315-0a7ba7ff2ded",
  "rental_contract_line_id": "d94b3143-8bf0-4691-ab22-7dae1428a7d4",
  "rental_status_history_id": "95b973af-cb81-4f40-8de0-00464e97ac2f",
  "quote": {
    "quote_id": "dryrun-1779231409328",
    "app_code": "RobotRentalStore",
    "model_code": "HD-R3",
    "model_name_ja": "Worker",
    "role_code": "Worker",
    "rental_unit": "hour",
    "duration_quantity": 1,
    "quantity": 1,
    "subtotal_jpy": 500,
    "discount_jpy": 0,
    "total_jpy": 500,
    "price_source": "prototype_default_until_price_catalog_connected"
  }
}