{"result":"error","error_code":"INTERNAL_ERROR","message":"ERROR:  Runtime control profile not found: app_surface_code=ai_company_manager, model_code=HD-R3\nCONTEXT:  PL/pgSQL function fn_runtime_execution_create_request(text,text,text,text,text,text,text,text,text) line 31 at RAISE\nPL/pgSQL function fn_runtime_execution_create_request_with_route_v1(text,text,text,text,text,text,text,text,text,text) line 5 at assignment","safety":{"external_execution_performed_flag":false,"pg_apply_performed_flag":false,"destructive_action_performed_flag":false}}